wiz_lib/__init__.py
wiz_lib/client.py
wiz_lib/discovery.py
wizlight_simple-0.1.2.dist-info/licenses/LICENSE
wizlight_simple-0.1.2.dist-info/METADATA
wizlight_simple-0.1.2.dist-info/WHEEL
wizlight_simple-0.1.2.dist-info/top_level.txt
wizlight_simple-0.1.2.dist-info/RECORD
