Metadata-Version: 2.4
Name: wizlight-simple
Version: 0.1.2
Summary: Asynchrone Library für WiZ-Geräte mit RGB, Szenen und zirkadianem Rhythmus
Author: David Block
License: MIT
Classifier: Programming Language :: Python :: 3
Classifier: License :: OSI Approved :: MIT License
Classifier: Operating System :: OS Independent
Classifier: Topic :: Home Automation
Requires-Python: >=3.8
License-File: LICENSE
Requires-Dist: zeroconf>=0.39.0
Dynamic: license-file
